py.typed
pyvq/__init__.py
pyvq/__init__.pyi
pyvq/py.typed
pyvq/pyvq.pypy39-pp73-aarch64-linux-gnu.so
pyvq-0.1.0.dist-info/METADATA
pyvq-0.1.0.dist-info/WHEEL
pyvq-0.1.0.dist-info/licenses/LICENSE
pyvq.pyi
pyvq-0.1.0.dist-info/RECORD
