Metadata-Version: 2.4
Name: pyvq
Version: 0.1.0
Classifier: Development Status :: 4 - Beta
Classifier: Intended Audience :: Developers
Classifier: Intended Audience :: Science/Research
Classifier: License :: OSI Approved :: MIT License
Classifier: Programming Language :: Python :: 3
Classifier: Programming Language :: Python :: 3.10
Classifier: Programming Language :: Python :: 3.11
Classifier: Programming Language :: Python :: 3.12
Classifier: Programming Language :: Python :: 3.13
Classifier: Programming Language :: Python :: 3.14
Classifier: Programming Language :: Rust
Classifier: Programming Language :: Python :: Implementation :: CPython
Classifier: Programming Language :: Python :: Implementation :: PyPy
Classifier: Topic :: Software Development :: Libraries
Classifier: Topic :: Software Development :: Libraries :: Python Modules
Classifier: Topic :: Scientific/Engineering :: Information Analysis
Classifier: Topic :: Scientific/Engineering :: Mathematics
Classifier: Topic :: Scientific/Engineering :: Artificial Intelligence
License-File: LICENSE
Summary: Python bindings for the Vq library
Keywords: vector-quantization,quantization,nearest-neighbor,data-compression,embeddings
Author-email: Hassan Abedi <hassan.abedi.t@gmail.com>
Maintainer-email: Hassan Abedi <hassan.abedi.t@gmail.com>
License: MIT
Requires-Python: >=3.10
Project-URL: documentation, https://github.com/CogitatorTech/vq
Project-URL: homepage, https://github.com/CogitatorTech/vq
Project-URL: repository, https://github.com/CogitatorTech/vq
